bandergoose/1-1.png
bandergoose/1-2.png
bandergoose/1-3.png
bandergoose/1-4.png
bandergoose/1-5.png
bandergoose/__init__.py
bandergoose/__main__.py
bandergoose/background.png
bandergoose/bandergoose.py
bandergoose/bonus.png
bandergoose/enemy.png
bandergoose/explosion.png
bandergoose/player.png
hanoitower/__init__.py
hanoitower/__main__.py
hanoitower/hanoitower.py
info.py
snake/__init__.py
snake/__main__.py
snake/snake.py
tictactoe/__init__.py
tictactoe/__main__.py
tictactoe/tictactoe.py
mini_gui_games-0.0.5.dist-info/LICENSE
mini_gui_games-0.0.5.dist-info/METADATA
mini_gui_games-0.0.5.dist-info/WHEEL
mini_gui_games-0.0.5.dist-info/entry_points.txt
mini_gui_games-0.0.5.dist-info/RECORD
